microservicemqtt/__init__.py
microservicemqtt/microservice.py
microservicemqtt/microserviceclient.py
microservicemqtt-0.1.10.dist-info/LICENSE
microservicemqtt-0.1.10.dist-info/METADATA
microservicemqtt-0.1.10.dist-info/WHEEL
microservicemqtt-0.1.10.dist-info/top_level.txt
microservicemqtt-0.1.10.dist-info/RECORD
