Metadata-Version: 2.1
Name: microservicemqtt
Version: 0.1.10
Summary: A microservice client/server implementation based on JSON-RPC over MQTT
Home-page: https://github.com/mrbluesky125/microservices-mqtt
Author: Timo Zimmermann
Author-email: github@timozimmermann.de
Project-URL: Bug Tracker, https://github.com/mrbluesky125/microservices-mqtt/issues
Classifier: Programming Language :: Python :: 3
Classifier: License :: OSI Approved :: MIT License
Classifier: Operating System :: OS Independent
Requires-Python: >=3.6
License-File: LICENSE
